odoo8_addon_document_wopi-8.0.1.0.0.99.dev1-py2.7-nspkg.pth
odoo8_addon_document_wopi-8.0.1.0.0.99.dev1.dist-info/METADATA
odoo8_addon_document_wopi-8.0.1.0.0.99.dev1.dist-info/RECORD
odoo8_addon_document_wopi-8.0.1.0.0.99.dev1.dist-info/WHEEL
odoo8_addon_document_wopi-8.0.1.0.0.99.dev1.dist-info/namespace_packages.txt
odoo8_addon_document_wopi-8.0.1.0.0.99.dev1.dist-info/top_level.txt
odoo_addons/document_wopi/README.rst
odoo_addons/document_wopi/__init__.py
odoo_addons/document_wopi/__openerp__.py
odoo_addons/document_wopi/controllers/__init__.py
odoo_addons/document_wopi/controllers/main.py
odoo_addons/document_wopi/data/ir_actions_todo.xml
odoo_addons/document_wopi/demo/ir_config_parameter.xml
odoo_addons/document_wopi/images/screenshot.png
odoo_addons/document_wopi/models/__init__.py
odoo_addons/document_wopi/models/document_wopi.py
odoo_addons/document_wopi/models/document_wopi_access_token.py
odoo_addons/document_wopi/models/knowledge_config_settings.py
odoo_addons/document_wopi/security/ir.model.access.csv
odoo_addons/document_wopi/security/ir_rule.xml
odoo_addons/document_wopi/static/description/icon.png
odoo_addons/document_wopi/static/src/css/document_wopi.css
odoo_addons/document_wopi/static/src/js/document_wopi.js
odoo_addons/document_wopi/static/src/xml/document_wopi.xml
odoo_addons/document_wopi/tests/__init__.py
odoo_addons/document_wopi/tests/test_document_wopi.py
odoo_addons/document_wopi/views/knowledge_config_settings.xml
odoo_addons/document_wopi/views/templates.xml
